LICENSE.txt
MANIFEST.in
README.md
requirements.txt
setup.cfg
setup.py
infer/__init__.py
infer/classify.py
infer/experiment.py
infer/nlp.py
infer.egg-info/PKG-INFO
infer.egg-info/SOURCES.txt
infer.egg-info/dependency_links.txt
infer.egg-info/requires.txt
infer.egg-info/top_level.txt
infer/tests/__init__.py
infer/tests/classify_test.py
infer/tests/experiment_test.py
infer/tests/nlp_test.py