Metadata-Version: 1.1
Name: infer
Version: 0.1
Summary: A machine learning toolkit for classification and assisted experimentation.
Home-page: http://www.github.com/bwbaugh/infer
Author: Wesley Baugh
Author-email: wesley@bwbaugh.com
License: Creative Commons Attribution-NonCommercial-ShareAlike 3.0 Unported License
Platform: UNKNOWN
Classifier: Development Status :: 2 - Pre-Alpha
Classifier: Intended Audience :: Developers
Classifier: Intended Audience :: Education
Classifier: Intended Audience :: Science/Research
Classifier: Natural Language :: English
Classifier: Programming Language :: Python
Classifier: Programming Language :: Python :: 2.7
Classifier: Programming Language :: Python :: Implementation :: PyPy
Classifier: Topic :: Scientific/Engineering :: Artificial Intelligence
Classifier: Topic :: Scientific/Engineering :: Information Analysis
Classifier: Topic :: Software Development :: Libraries :: Python Modules
Classifier: Topic :: Text Processing :: Linguistic
